[
 {
   "N": 1,
   "FirstName": "Dulce",
   "LastName": "Abril",
   "Gender": "Female",
   "Country": "United States",
   "Age": 32,
   "Date": "15/10/2017",
   "Id": 1562
 },
 {
   "N": 2,
   "FirstName": "Mara",
   "LastName": "Hashimoto",
   "Gender": "Female",
   "Country": "Great Britain",
   "Age": 25,
   "Date": "16/08/2016",
   "Id": 1582
 },
 {
   "N": 3,
   "FirstName": "Philip",
   "LastName": "Gent",
   "Gender": "Male",
   "Country": "France",
   "Age": 36,
   "Date": "21/05/2015",
   "Id": 2587
 },
 {
   "N": 4,
   "FirstName": "Kathleen",
   "LastName": "Hanner",
   "Gender": "Female",
   "Country": "United States",
   "Age": 25,
   "Date": "15/10/2017",
   "Id": 3549
 },
 {
   "N": 5,
   "FirstName": " Nereida",
   "LastName": " Magwood",
   "Gender": " Female",
   "Country": " United States",
   "Age": 58,
   "Date": " 16/08/2016",
   "Id": 2468
 },
 {
   "N": 6,
   "FirstName": "Gaston",
   "LastName": "Brumm",
   "Gender": "Male",
   "Country": "United States",
   "Age": 24,
   "Date": "21/05/2015",
   "Id": 2554
 },
 {
   "N": 7,
   "FirstName": "Etta",
   "LastName": "Hurn",
   "Gender": "Female",
   "Country": "Great Britain",
   "Age": 56,
   "Date": "15/10/2017",
   "Id": 3598
 },
 {
   "N": 8,
   "FirstName": "Earlean",
   "LastName": "Melgar",
   "Gender": "Female",
   "Country": "United States",
   "Age": 27,
   "Date": "16/08/2016",
   "Id": 2456
 },
 {
   "N": 9,
   "FirstName": "Vincenza",
   "LastName": "Weiland",
   "Gender": "Female",
   "Country": "United States",
   "Age": 40,
   "Date": "21/05/2015",
   "Id": 6548
 },
 {
   "N": 10,
   "FirstName": "Fallon",
   "LastName": "Winward",
   "Gender": "Female",
   "Country": "Great Britain",
   "Age": 28,
   "Date": "16/08/2016",
   "Id": 5486
 }
]